README
setup.py
pypatch/__init__.py
pypatch/command.py
pypatch/patch.py
pypatch.egg-info/PKG-INFO
pypatch.egg-info/SOURCES.txt
pypatch.egg-info/dependency_links.txt
pypatch.egg-info/entry_points.txt
pypatch.egg-info/requires.txt
pypatch.egg-info/top_level.txt