Metadata-Version: 1.1
Name: pypatch
Version: 1.0.1
Summary: Utility to apply unified diff patches to installed python modules.
Home-page: http://sitkatech.com
Author: Sitka Technology Group
Author-email: info@sitkatech.com
License: MIT
Keywords: build tool patch unified diff
Platform: UNKNOWN
Classifier: License :: OSI Approved :: MIT License
Classifier: Topic :: Software Development :: Build Tools
Classifier: Topic :: Utilities
Classifier: Intended Audience :: Developers
Classifier: Natural Language :: English
Classifier: Programming Language :: Python :: 2.7
Classifier: Programming Language :: Python :: 3
